<?xml version="1.0" encoding="utf-8"?>
<Protocol>
  <ProtocolName>Axial scanning_child</ProtocolName>
  <ProtocolID>38173564-3f95-47f3-bcd5-04d707281164</ProtocolID>
  <ExamPartID>9709f7ad-bb20-4266-a5ac-34003df4a978</ExamPartID>
  <ScanMode>Axial scanning</ScanMode>
  <PatientPosition>HFS</PatientPosition>
  <BodySize>Child</BodySize>
  <Description>test</Description>
  <IsTabletSuitable>0</IsTabletSuitable>
  <IsEnhanced>0</IsEnhanced>
  <IsEmergency>0</IsEmergency>
  <IsFactory>1</IsFactory>
  <IsValid>1</IsValid>
  <ProtocolFamily>CEye24</ProtocolFamily>
  <SortID>9</SortID>
  <ScanEntry ScanType="Scan">
    <ScanRange>Head</ScanRange>
    <MA>40</MA>
    <KV>80</KV>
    <ScanDirection>Head-Foot</ScanDirection>
    <PatientPosition>HFS</PatientPosition>
    <TubePosition>Top</TubePosition>
    <ScanLength>120</ScanLength>
    <TableStartPosition>200</TableStartPosition>
    <TableEndPosition>0</TableEndPosition>
    <TableHeight>0.0</TableHeight>
    <DelayTime>0</DelayTime>
    <ScanMode>Axial scanning</ScanMode>
    <BinningMode>1x1</BinningMode>
    <ExpMode>Single point</ExpMode>
    <FrameNum>1080</FrameNum>
    <FrameTime>10</FrameTime>
    <ExpTime>6</ExpTime>
    <OverSample>0</OverSample>
    <Pitch>3</Pitch>
    <AngleSpeed>274</AngleSpeed>
    <ExpSum>1</ExpSum>
    <TableSpeed>60</TableSpeed>
    <ReconJob>
      <SeriesDescription>Rcon Head555</SeriesDescription>
      <SliceThickness>0.65</SliceThickness>
      <Kernel>Sharp+</Kernel>
      <Window>Head</Window>
      <Width>512</Width>
      <Height>512</Height>
      <Increment>10</Increment>
      <WindowCenter>-800</WindowCenter>
      <WindowWidth>400</WindowWidth>
      <ImageOrder>Head-Foot</ImageOrder>
      <VoxelSizeXY>0.656</VoxelSizeXY>
      <DenoiseCoef>20</DenoiseCoef>
      <FOV>350.0</FOV>
      <Center-X>350</Center-X>
      <Center-Y>350</Center-Y>
      <ProtocolType>0</ProtocolType>
    </ReconJob>
  </ScanEntry>
  <ScanEntry ScanType="Topo">
    <ScanRange>Topogram</ScanRange>
    <MA>50</MA>
    <KV>80</KV>
    <ScanDirection>Head-Foot</ScanDirection>
    <PatientPosition>HFS</PatientPosition>
    <TubePosition>Top</TubePosition>
    <ScanLength>120</ScanLength>
    <TableStartPosition>0</TableStartPosition>
    <TableEndPosition>300</TableEndPosition>
    <TableHeight>0.0</TableHeight>
    <DelayTime>0</DelayTime>
    <ScanMode>Topogram</ScanMode>
    <BinningMode>1x1</BinningMode>
    <ExpMode>Independent</ExpMode>
    <FrameNum>360</FrameNum>
    <FrameTime>10</FrameTime>
    <ExpTime>10</ExpTime>
    <OverSample>0</OverSample>
    <Pitch>1.0</Pitch>
    <AngleSpeed>274</AngleSpeed>
    <ExpSum>1</ExpSum>
    <TableSpeed>60</TableSpeed>
    <ReconJob>
      <SeriesDescription>Rcon top1</SeriesDescription>
      <SliceThickness>0.16</SliceThickness>
      <Kernel>2</Kernel>
      <Window>Heade</Window>
      <Width>512</Width>
      <Height>512</Height>
      <Increment>10</Increment>
      <WindowCenter>600</WindowCenter>
      <WindowWidth>520</WindowWidth>
      <ImageOrder>CranioCaudal</ImageOrder>
      <VoxelSizeXY>0.328</VoxelSizeXY>
      <DenoiseCoef>20</DenoiseCoef>
      <FOV>350.0</FOV>
      <Center-X>350</Center-X>
      <Center-Y>350</Center-Y>
      <ProtocolType>0</ProtocolType>
    </ReconJob>
  </ScanEntry>
</Protocol>